ueqplusanalyze/__init__.py
ueqplusanalyze/analyzer.py
ueqplusanalyze-0.0.3.dist-info/METADATA
ueqplusanalyze-0.0.3.dist-info/WHEEL
ueqplusanalyze-0.0.3.dist-info/licenses/LICENSE
ueqplusanalyze-0.0.3.dist-info/RECORD
