Metadata-Version: 2.1
Name: ueqplusanalyze
Version: 0.0.3
Summary: Create statical analysis for UEQ+ data
Project-URL: Homepage, https://github.com/B3J4y/ueq-plus-data-analyze
Project-URL: Bug Tracker, https://github.com/B3J4y/ueq-plus-data-analyze/issues
Author-email: Jan Bernoth <jan.bernoth@uni-potsdam.de>, Lewin Kästner <lewin.kaestner@uni-potsdam.de>
License-File: LICENSE
Classifier: License :: OSI Approved :: MIT License
Classifier: Operating System :: OS Independent
Classifier: Programming Language :: Python :: 3
Requires-Python: >=3.8
Requires-Dist: jupyter==1.0.0
Requires-Dist: matplotlib==3.6.2
Requires-Dist: numpy==1.23.5
Requires-Dist: pandas==1.5.2
Requires-Dist: pytest==7.2.1
